sophus/__init__.py
sophus/geometry.proto
sophus/geometry_pb2.py
sophus/geometry_pb2_grpc.py
sophus/image.proto
sophus/image_pb2.py
sophus/image_pb2_grpc.py
sophus/lie.proto
sophus/lie_pb2.py
sophus/lie_pb2_grpc.py
sophus/linalg.proto
sophus/linalg_pb2.py
sophus/linalg_pb2_grpc.py
sophus/sensor.proto
sophus/sensor_pb2.py
sophus/sensor_pb2_grpc.py
sophus-23.0.1.dist-info/METADATA
sophus-23.0.1.dist-info/WHEEL
sophus-23.0.1.dist-info/top_level.txt
sophus-23.0.1.dist-info/RECORD
